torchmx/__init__.py
torchmx/config.py
torchmx/custom_float_cast.py
torchmx/dtypes.py
torchmx/env_variables.py
torchmx/mx_quantization_utils.py
torchmx/mx_tensor.py
torchmx/ops.py
torchmx/quant_api.py
torchmx/utils.py
torchmx/layers/__init__.py
torchmx/layers/mx_linear.py
torchmx/layers/mx_llama_attention.py
torchmx/layers/mx_qwen2_attention.py
torchmx-0.1.0.dist-info/METADATA
torchmx-0.1.0.dist-info/WHEEL
torchmx-0.1.0.dist-info/licenses/LICENSE
torchmx-0.1.0.dist-info/RECORD
