Metadata-Version: 2.4
Name: torchmx
Version: 0.1.0
Summary: PyTorch Quantization Framework For OCP MX Datatypes.
Author-email: Abhijit Balaji <abhijit@rain.ai>, Marios Fournarakis <marios@rain.ai>
License-File: LICENSE
Requires-Python: >=3.11
Requires-Dist: accelerate>=1.7.0
Requires-Dist: attrs>=25.3.0
Requires-Dist: flaky>=3.8.1
Requires-Dist: mkdocs-material>=9.6.5
Requires-Dist: mkdocs>=1.6.1
Requires-Dist: pre-commit>=4.2.0
Requires-Dist: pydoc-markdown>=4.8.2
Requires-Dist: pytest>=8.3.5
Requires-Dist: setuptools>=80.8.0
Requires-Dist: tabulate>=0.9.0
Requires-Dist: torch>=2.5.1
Requires-Dist: torchao==0.6.1
Requires-Dist: transformers==4.44.2
